python_color_transfer/color_transfer.py
python_color_transfer/utils.py
python_color_transfer-0.1.2a0.dist-info/LICENSE
python_color_transfer-0.1.2a0.dist-info/WHEEL
python_color_transfer-0.1.2a0.dist-info/METADATA
python_color_transfer-0.1.2a0.dist-info/RECORD
