Metadata-Version: 2.1
Name: python-color-transfer
Version: 0.1.2a0
Summary: Three methods of color transfer implemented in python.
License: MIT
Author: pengbo-learn
Requires-Python: >=3.6,<4.0
Classifier: License :: OSI Approved :: MIT License
Classifier: Programming Language :: Python :: 3
Classifier: Programming Language :: Python :: 3.10
Classifier: Programming Language :: Python :: 3.6
Classifier: Programming Language :: Python :: 3.7
Classifier: Programming Language :: Python :: 3.8
Classifier: Programming Language :: Python :: 3.9
Requires-Dist: numpy (>=1.19,<2.0)
Requires-Dist: opencv-python (>=4.2,<5.0)
